django/contrib/__init__.py
django/contrib/my_app/__init__.py
django/contrib/my_app/apps.py
django/contrib/my_app/urls.py
django/contrib/my_app/views.py
django/contrib/my_app/management/__init__.py
django/contrib/my_app/management/commands/__init__.py
django/contrib/my_app/management/commands/test_command.py
django_test_contrib-0.1.0.dist-info/METADATA
django_test_contrib-0.1.0.dist-info/WHEEL
django_test_contrib-0.1.0.dist-info/licenses/LICENSE
django_test_contrib-0.1.0.dist-info/RECORD
