Metadata-Version: 2.3
Name: django-test-contrib
Version: 0.1.0
Summary: A test package for adding a package to Django contrib
Project-URL: Homepage, https://github.com/softwarecrafts/django-cptemplate
Project-URL: Repository, https://github.com/softwarecrafts/django-cptemplate
Author-email: Andrew Miller <andrew@softwarecrafts.co.uk>
License: MIT License
License-File: LICENSE
Classifier: Development Status :: 1 - Planning
Classifier: Environment :: Web Environment
Classifier: Framework :: Django
Classifier: Framework :: Django :: 3.2
Classifier: Framework :: Django :: 4.2
Classifier: Framework :: Django :: 5.0
Classifier: Intended Audience :: Developers
Classifier: License :: OSI Approved :: BSD License
Classifier: Operating System :: OS Independent
Classifier: Programming Language :: Python
Classifier: Programming Language :: Python :: 3 :: Only
Classifier: Programming Language :: Python :: 3.8
Classifier: Programming Language :: Python :: 3.9
Classifier: Programming Language :: Python :: 3.10
Classifier: Programming Language :: Python :: 3.11
Classifier: Programming Language :: Python :: 3.12
Classifier: Topic :: Software Development :: Libraries :: Python Modules
Requires-Dist: django
